stepmaker/__init__.py
stepmaker/addr.py
stepmaker/buzzer.py
stepmaker/dht.py
stepmaker/driver.py
stepmaker/lcd.py
stepmaker/pico.py
stepmaker/rtc.py
stepmaker/ultrasound.py
micropython_stepmaker-0.0.9.dist-info/METADATA
micropython_stepmaker-0.0.9.dist-info/WHEEL
micropython_stepmaker-0.0.9.dist-info/top_level.txt
micropython_stepmaker-0.0.9.dist-info/RECORD
