Metadata-Version: 2.1
Name: micropython-stepmaker
Version: 0.0.9
Summary: Stepmaker Package For Stepmaker Kit Users and Rpi Pico Users.
Home-page: UNKNOWN
Author: HwangJungeon
Author-email: hje@takeup.cc
License: CC BY-NC-SA 4.0
Keywords: stepmaker,step,maker,micropython
Platform: UNKNOWN
